<?xml version="1.0" encoding="utf-8" ?>
<dwsync>
<file name="fa-brands-400.eot" server="//dev.orau.net/RSB/PFAiRD/" local="131740120920000000" remote="131740120920000000" Dst="2" />
<file name="fa-brands-400.svg" server="//dev.orau.net/RSB/PFAiRD/" local="131740120920000000" remote="131740120920000000" Dst="2" />
<file name="fa-brands-400.ttf" server="//dev.orau.net/RSB/PFAiRD/" local="131740120920000000" remote="131740120920000000" Dst="2" />
<file name="fa-brands-400.woff" server="//dev.orau.net/RSB/PFAiRD/" local="131740120920000000" remote="131740120920000000" Dst="2" />
<file name="fa-brands-400.woff2" server="//dev.orau.net/RSB/PFAiRD/" local="131740120920000000" remote="131740120920000000" Dst="2" />
<file name="fa-regular-400.eot" server="//dev.orau.net/RSB/PFAiRD/" local="131740120920000000" remote="131740120920000000" Dst="2" />
<file name="fa-regular-400.svg" server="//dev.orau.net/RSB/PFAiRD/" local="131740120920000000" remote="131740120920000000" Dst="2" />
<file name="fa-regular-400.ttf" server="//dev.orau.net/RSB/PFAiRD/" local="131740120920000000" remote="131740120920000000" Dst="2" />
<file name="fa-regular-400.woff" server="//dev.orau.net/RSB/PFAiRD/" local="131740120920000000" remote="131740120920000000" Dst="2" />
<file name="fa-regular-400.woff2" server="//dev.orau.net/RSB/PFAiRD/" local="131740120920000000" remote="131740120920000000" Dst="2" />
<file name="fa-solid-900.eot" server="//dev.orau.net/RSB/PFAiRD/" local="131740120920000000" remote="131740120920000000" Dst="2" />
<file name="fa-solid-900.svg" server="//dev.orau.net/RSB/PFAiRD/" local="131740120920000000" remote="131740120920000000" Dst="2" />
<file name="fa-solid-900.ttf" server="//dev.orau.net/RSB/PFAiRD/" local="131740120920000000" remote="131740120920000000" Dst="2" />
<file name="fa-solid-900.woff" server="//dev.orau.net/RSB/PFAiRD/" local="131740120920000000" remote="131740120920000000" Dst="2" />
<file name="fa-solid-900.woff2" server="//dev.orau.net/RSB/PFAiRD/" local="131740120920000000" remote="131740120920000000" Dst="2" />
</dwsync>